pdroot/__init__.py
pdroot/accessors.py
pdroot/draw.py
pdroot/parse.py
pdroot/readwrite.py
pdroot-1.12.0.dist-info/METADATA
pdroot-1.12.0.dist-info/WHEEL
pdroot-1.12.0.dist-info/top_level.txt
pdroot-1.12.0.dist-info/RECORD
