Metadata-Version: 2.1
Name: pdroot
Version: 1.12.0
Summary: utilities for working with ROOT files and pandas
Home-page: https://github.com/aminnj/pdroot
Author: Nick Amin
Author-email: amin.nj@gmail.com
License: BSD
Download-URL: https://github.com/aminnj/pdroot/tarball/1.12.0
Platform: UNKNOWN
Classifier: License :: OSI Approved :: MIT License
Classifier: Development Status :: 3 - Alpha
Classifier: Intended Audience :: Developers
Classifier: Programming Language :: Python :: 3
Classifier: Programming Language :: Python :: 2.7
Requires-Dist: astor
Requires-Dist: numpy
Requires-Dist: xxhash
Requires-Dist: lz4
Requires-Dist: uproot3
Requires-Dist: uproot4
Requires-Dist: uproot3-methods
Requires-Dist: awkward0
Requires-Dist: awkward1
Requires-Dist: awkward (>=1.0.2)
Requires-Dist: fletcher
Requires-Dist: pyarrow
Requires-Dist: pandas
Requires-Dist: yahist (>=1.8.0)
Requires-Dist: tqdm
